data2notion_main.py
data2notion/__init__.py
data2notion/serialization.py
data2notion/plugins/__init__.py
data2notion/plugins/csv_plugin.py
data2notion/plugins/json_plugin.py
data2notion/plugins/plugin.py
data2notion/plugins/prometheus_plugin.py
data2notion-1.3.3.dist-info/METADATA
data2notion-1.3.3.dist-info/WHEEL
data2notion-1.3.3.dist-info/entry_points.txt
data2notion-1.3.3.dist-info/licenses/LICENSE
data2notion-1.3.3.dist-info/RECORD
