Metadata-Version: 2.4
Name: data2notion
Version: 1.3.3
Summary: Synchronize your data with a Notion database
Project-URL: Homepage, https://github.com/pierresouchay/data2notion
Project-URL: Issues, https://github.com/pierresouchay/data2notion/issues
Author-email: Pierre Souchay <pierre@souchay.net>
License-File: LICENSE
Classifier: License :: OSI Approved :: MIT License
Classifier: Operating System :: OS Independent
Classifier: Programming Language :: Python :: 3
Requires-Python: >=3.9
Requires-Dist: asynciolimiter>=1.2.0
Requires-Dist: click
Requires-Dist: notion-client<2.6
Provides-Extra: dev
Requires-Dist: build; extra == 'dev'
Requires-Dist: flake8~=7.2; extra == 'dev'
Requires-Dist: isort~=6.0; extra == 'dev'
Requires-Dist: mypy~=1.15.0; extra == 'dev'
Requires-Dist: pylint~=3.3.6; extra == 'dev'
Requires-Dist: ruff~=0.11.4; extra == 'dev'
Requires-Dist: twine; extra == 'dev'
